trytond/modules/akademy_party/LICENSE
trytond/modules/akademy_party/README.md
trytond/modules/akademy_party/__init__.py
trytond/modules/akademy_party/party.py
trytond/modules/akademy_party/party.xml
trytond/modules/akademy_party/tryton.cfg
trytond/modules/akademy_party/locale/en.po
trytond/modules/akademy_party/locale/fr.po
trytond/modules/akademy_party/locale/pt.po
trytond/modules/akademy_party/security/access_rights_admin.xml
trytond/modules/akademy_party/security/access_rights_direct.xml
trytond/modules/akademy_party/security/access_rights_secret.xml
trytond/modules/akademy_party/security/access_rights_student.xml
trytond/modules/akademy_party/security/access_rights_teacher.xml
trytond/modules/akademy_party/tests/__init__.py
trytond/modules/akademy_party/tests/test_party.py
trytond/modules/akademy_party/view/party_form.xml
trytond/modules/akademy_party/view/party_tree.xml
akademy_party-1.1.0.dist-info/METADATA
akademy_party-1.1.0.dist-info/WHEEL
akademy_party-1.1.0.dist-info/licenses/LICENSE
akademy_party-1.1.0.dist-info/RECORD
