Metadata-Version: 2.4
Name: akademy_party
Version: 1.1.0
Summary: SAGE Education is a free and open-source project for educators, educational institutions, and governments.
Project-URL: Homepage, https://comunidadedosaber.ao
Project-URL: Documentation, https://docs.comunidadedosaber.ao
Project-URL: Demo, https://sage.comunidadedosaber.ao
Project-URL: Repository, https://github.com/zacariasjuliano/akademy-party
Project-URL: Bug Tracker, https://github.com/zacariasjuliano/akademy-party/issues
Project-URL: Changelog, https://github.com/zacariasjuliano/akademy-party/blob/main/CHANGELOG.md
Author-email: Zacarias Juliano Capingala <zacariasjuliano@gmail.com>
License: GPL-3.0-or-later
License-File: LICENSE
Requires-Python: >=3.8
Requires-Dist: psycopg2-binary>=2.9.11
Requires-Dist: pycountry>=24.6.1
Requires-Dist: trytond-country==7.0
Requires-Dist: trytond-party==7.0
Requires-Dist: trytond==7.0.0
